pycites/__init__.py
pycites/cites_download.py
pycites/cli.py
pycites-0.1.4.dist-info/entry_points.txt
pycites-0.1.4.dist-info/LICENSE
pycites-0.1.4.dist-info/WHEEL
pycites-0.1.4.dist-info/METADATA
pycites-0.1.4.dist-info/RECORD
