Metadata-Version: 2.1
Name: pycites
Version: 0.1.4
Summary: Package to download and interact with the CITES Trade Database in Python
Home-page: https://github.com/ltirrell/pycites
License: MIT
Author: Lee Tirrell
Author-email: tirrell.le@gmail.com
Requires-Python: >=3.7.1,<4.0.0
Classifier: License :: OSI Approved :: MIT License
Classifier: Programming Language :: Python :: 3
Classifier: Programming Language :: Python :: 3.10
Classifier: Programming Language :: Python :: 3.8
Classifier: Programming Language :: Python :: 3.9
Classifier: Topic :: Software Development :: Libraries :: Python Modules
Requires-Dist: appdirs (>=1.4.4,<2.0.0)
Requires-Dist: click (>=7.0)
Requires-Dist: pandas (>=1.2,<2.0)
Requires-Dist: requests (>=2.24.0,<3.0.0)
Requires-Dist: tqdm (>=4.46.1,<5.0.0)
Project-URL: Repository, https://github.com/ltirrell/pycites
